latexqol/__init__.py
latexqol/conversion.py
latexqol-0.0.2.dist-info/LICENSE
latexqol-0.0.2.dist-info/METADATA
latexqol-0.0.2.dist-info/WHEEL
latexqol-0.0.2.dist-info/top_level.txt
latexqol-0.0.2.dist-info/RECORD
