Metadata-Version: 2.1
Name: latexqol
Version: 0.0.2
Summary: A module for moving data into LaTeX formated text.
Home-page: https://github.com/konradgj/latexqol
Author: Konrad
Author-email: 
License: UNKNOWN
Platform: UNKNOWN
Classifier: Programming Language :: Python :: 3
Classifier: License :: OSI Approved :: MIT License
Classifier: Operating System :: OS Independent
Requires-Python: >=3.6
Requires-Dist: pyperclip
